{
  "updated": "2026-05-04T22:30:23Z",
  "portfolio": {
    "total_invested_eur": 1896.06,
    "total_value_eur": 2287.8,
    "cash_eur": 95.61,
    "total_with_cash": 2383.41,
    "pnl_eur": 391.74,
    "pnl_pct": 20.66,
    "fx_eurusd": 1.1695,
    "positions": [
      {
        "symbol": "NVDA",
        "name": "Nvidia",
        "shares": 4,
        "entry_usd": 191.12,
        "entry_eur": 162.01,
        "current_usd": 198.48,
        "current_eur": 169.72,
        "invested_eur": 648.04,
        "value_eur": 678.88,
        "pnl_eur": 30.84,
        "pnl_pct": 4.76,
        "change_today_pct": 0.02
      },
      {
        "symbol": "GOOGL",
        "name": "Alphabet",
        "shares": 1,
        "entry_usd": 314.19,
        "entry_eur": 266.33,
        "current_usd": 383.25,
        "current_eur": 327.72,
        "invested_eur": 266.33,
        "value_eur": 327.72,
        "pnl_eur": 61.39,
        "pnl_pct": 23.05,
        "change_today_pct": -0.63
      },
      {
        "symbol": "TSM",
        "name": "TSMC",
        "shares": 1,
        "entry_usd": 368.62,
        "entry_eur": 312.47,
        "current_usd": 401.61,
        "current_eur": 343.42,
        "invested_eur": 312.47,
        "value_eur": 343.42,
        "pnl_eur": 30.95,
        "pnl_pct": 9.9,
        "change_today_pct": 0.99
      },
      {
        "symbol": "AMD",
        "name": "Advanced Micro Devices",
        "shares": 2,
        "entry_usd": 196.18,
        "entry_eur": 166.25,
        "current_usd": 341.54,
        "current_eur": 292.05,
        "invested_eur": 332.5,
        "value_eur": 584.1,
        "pnl_eur": 251.6,
        "pnl_pct": 75.67,
        "change_today_pct": -5.27
      },
      {
        "symbol": "MSFT",
        "name": "Microsoft",
        "shares": 1,
        "entry_usd": 397.23,
        "entry_eur": 336.72,
        "current_usd": 413.62,
        "current_eur": 353.69,
        "invested_eur": 336.72,
        "value_eur": 353.69,
        "pnl_eur": 16.97,
        "pnl_pct": 5.04,
        "change_today_pct": -0.2
      }
    ]
  },
  "crypto": {
    "available": true,
    "total_eur": 599.41,
    "holdings": [
      {
        "symbol": "TRUMP",
        "name": "TRUMP",
        "amount": 152.12063257,
        "price_eur": 2.0,
        "value_eur": 304.07
      },
      {
        "symbol": "EUR",
        "name": "Euro",
        "amount": 277.84,
        "price_eur": 1.0,
        "value_eur": 277.84
      },
      {
        "symbol": "LINK",
        "name": "LINK",
        "amount": 1.10853955,
        "price_eur": 8.03,
        "value_eur": 8.91
      },
      {
        "symbol": "SOL",
        "name": "SOL",
        "amount": 0.11908588,
        "price_eur": 72.14,
        "value_eur": 8.59
      }
    ]
  }
}