{
  "updated": "2026-04-02T12:48:34Z",
  "portfolio": {
    "total_invested_eur": 1896.06,
    "total_value_eur": 1848.8,
    "cash_eur": 95.61,
    "total_with_cash": 1944.41,
    "pnl_eur": -47.26,
    "pnl_pct": -2.49,
    "fx_eurusd": 1.153,
    "positions": [
      {
        "symbol": "NVDA",
        "name": "Nvidia",
        "shares": 4,
        "entry_usd": 191.12,
        "entry_eur": 162.01,
        "current_usd": 175.75,
        "current_eur": 152.43,
        "invested_eur": 648.04,
        "value_eur": 609.71,
        "pnl_eur": -38.33,
        "pnl_pct": -5.91,
        "change_today_pct": 0.77
      },
      {
        "symbol": "GOOGL",
        "name": "Alphabet",
        "shares": 1,
        "entry_usd": 314.19,
        "entry_eur": 266.33,
        "current_usd": 297.39,
        "current_eur": 257.93,
        "invested_eur": 266.33,
        "value_eur": 257.93,
        "pnl_eur": -8.4,
        "pnl_pct": -3.16,
        "change_today_pct": 3.42
      },
      {
        "symbol": "TSM",
        "name": "TSMC",
        "shares": 1,
        "entry_usd": 368.62,
        "entry_eur": 312.47,
        "current_usd": 341.49,
        "current_eur": 296.17,
        "invested_eur": 312.47,
        "value_eur": 296.17,
        "pnl_eur": -16.3,
        "pnl_pct": -5.22,
        "change_today_pct": 1.05
      },
      {
        "symbol": "AMD",
        "name": "Advanced Micro Devices",
        "shares": 2,
        "entry_usd": 196.18,
        "entry_eur": 166.25,
        "current_usd": 210.21,
        "current_eur": 182.32,
        "invested_eur": 332.5,
        "value_eur": 364.63,
        "pnl_eur": 32.13,
        "pnl_pct": 9.66,
        "change_today_pct": 3.33
      },
      {
        "symbol": "MSFT",
        "name": "Microsoft",
        "shares": 1,
        "entry_usd": 397.23,
        "entry_eur": 336.72,
        "current_usd": 369.37,
        "current_eur": 320.35,
        "invested_eur": 336.72,
        "value_eur": 320.35,
        "pnl_eur": -16.37,
        "pnl_pct": -4.86,
        "change_today_pct": -0.22
      }
    ]
  },
  "crypto": {
    "available": true,
    "total_eur": 622.14,
    "holdings": [
      {
        "symbol": "TRUMP",
        "name": "TRUMP",
        "amount": 152.11367438,
        "price_eur": 2.45,
        "value_eur": 373.2
      },
      {
        "symbol": "SOL",
        "name": "SOL",
        "amount": 3.41296474,
        "price_eur": 67.82,
        "value_eur": 231.47
      },
      {
        "symbol": "EUR",
        "name": "Euro",
        "amount": 11.06,
        "price_eur": 1.0,
        "value_eur": 11.06
      },
      {
        "symbol": "LINK",
        "name": "LINK",
        "amount": 0.86982894,
        "price_eur": 7.37,
        "value_eur": 6.41
      }
    ]
  }
}