{
  "updated": "2026-04-07T15:42:12Z",
  "portfolio": {
    "total_invested_eur": 1896.06,
    "total_value_eur": 1848.11,
    "cash_eur": 95.61,
    "total_with_cash": 1943.72,
    "pnl_eur": -47.95,
    "pnl_pct": -2.53,
    "fx_eurusd": 1.1575,
    "positions": [
      {
        "symbol": "NVDA",
        "name": "Nvidia",
        "shares": 4,
        "entry_usd": 191.12,
        "entry_eur": 162.01,
        "current_usd": 174.77,
        "current_eur": 150.98,
        "invested_eur": 648.04,
        "value_eur": 603.94,
        "pnl_eur": -44.1,
        "pnl_pct": -6.81,
        "change_today_pct": -1.62
      },
      {
        "symbol": "GOOGL",
        "name": "Alphabet",
        "shares": 1,
        "entry_usd": 314.19,
        "entry_eur": 266.33,
        "current_usd": 300.27,
        "current_eur": 259.4,
        "invested_eur": 266.33,
        "value_eur": 259.4,
        "pnl_eur": -6.93,
        "pnl_pct": -2.6,
        "change_today_pct": 0.09
      },
      {
        "symbol": "TSM",
        "name": "TSMC",
        "shares": 1,
        "entry_usd": 368.62,
        "entry_eur": 312.47,
        "current_usd": 337.27,
        "current_eur": 291.36,
        "invested_eur": 312.47,
        "value_eur": 291.36,
        "pnl_eur": -21.11,
        "pnl_pct": -6.75,
        "change_today_pct": -1.32
      },
      {
        "symbol": "AMD",
        "name": "Advanced Micro Devices",
        "shares": 2,
        "entry_usd": 196.18,
        "entry_eur": 166.25,
        "current_usd": 217.28,
        "current_eur": 187.71,
        "invested_eur": 332.5,
        "value_eur": 375.42,
        "pnl_eur": 42.92,
        "pnl_pct": 12.91,
        "change_today_pct": -1.32
      },
      {
        "symbol": "MSFT",
        "name": "Microsoft",
        "shares": 1,
        "entry_usd": 397.23,
        "entry_eur": 336.72,
        "current_usd": 368.09,
        "current_eur": 317.99,
        "invested_eur": 336.72,
        "value_eur": 317.99,
        "pnl_eur": -18.73,
        "pnl_pct": -5.56,
        "change_today_pct": -1.28
      }
    ]
  },
  "crypto": {
    "available": true,
    "total_eur": 631.92,
    "holdings": [
      {
        "symbol": "TRUMP",
        "name": "TRUMP",
        "amount": 152.11484105,
        "price_eur": 2.45,
        "value_eur": 373.37
      },
      {
        "symbol": "SOL",
        "name": "SOL",
        "amount": 3.51964192,
        "price_eur": 68.09,
        "value_eur": 239.66
      },
      {
        "symbol": "EUR",
        "name": "Euro",
        "amount": 11.44,
        "price_eur": 1.0,
        "value_eur": 11.44
      },
      {
        "symbol": "LINK",
        "name": "LINK",
        "amount": 1.00005527,
        "price_eur": 7.46,
        "value_eur": 7.46
      }
    ]
  }
}