{
  "updated": "2026-03-31T18:35:32Z",
  "portfolio": {
    "total_invested_eur": 1896.06,
    "total_value_eur": 1807.32,
    "cash_eur": 95.61,
    "total_with_cash": 1902.93,
    "pnl_eur": -88.74,
    "pnl_pct": -4.68,
    "fx_eurusd": 1.1546,
    "positions": [
      {
        "symbol": "NVDA",
        "name": "Nvidia",
        "shares": 4,
        "entry_usd": 191.12,
        "entry_eur": 162.01,
        "current_usd": 173.14,
        "current_eur": 149.96,
        "invested_eur": 648.04,
        "value_eur": 599.83,
        "pnl_eur": -48.21,
        "pnl_pct": -7.44,
        "change_today_pct": 4.83
      },
      {
        "symbol": "GOOGL",
        "name": "Alphabet",
        "shares": 1,
        "entry_usd": 314.19,
        "entry_eur": 266.33,
        "current_usd": 286.7,
        "current_eur": 248.31,
        "invested_eur": 266.33,
        "value_eur": 248.31,
        "pnl_eur": -18.02,
        "pnl_pct": -6.77,
        "change_today_pct": 4.83
      },
      {
        "symbol": "TSM",
        "name": "TSMC",
        "shares": 1,
        "entry_usd": 368.62,
        "entry_eur": 312.47,
        "current_usd": 333.56,
        "current_eur": 288.89,
        "invested_eur": 312.47,
        "value_eur": 288.89,
        "pnl_eur": -23.58,
        "pnl_pct": -7.55,
        "change_today_pct": 5.39
      },
      {
        "symbol": "AMD",
        "name": "Advanced Micro Devices",
        "shares": 2,
        "entry_usd": 196.18,
        "entry_eur": 166.25,
        "current_usd": 202.07,
        "current_eur": 175.01,
        "invested_eur": 332.5,
        "value_eur": 350.03,
        "pnl_eur": 17.53,
        "pnl_pct": 5.27,
        "change_today_pct": 3.08
      },
      {
        "symbol": "MSFT",
        "name": "Microsoft",
        "shares": 1,
        "entry_usd": 397.23,
        "entry_eur": 336.72,
        "current_usd": 369.78,
        "current_eur": 320.27,
        "invested_eur": 336.72,
        "value_eur": 320.27,
        "pnl_eur": -16.45,
        "pnl_pct": -4.89,
        "change_today_pct": 3.01
      }
    ]
  },
  "crypto": {
    "available": true,
    "total_eur": 640.47,
    "holdings": [
      {
        "symbol": "TRUMP",
        "name": "TRUMP",
        "amount": 152.11367438,
        "price_eur": 2.59,
        "value_eur": 394.55
      },
      {
        "symbol": "SOL",
        "name": "SOL",
        "amount": 3.19323274,
        "price_eur": 71.63,
        "value_eur": 228.73
      },
      {
        "symbol": "EUR",
        "name": "Euro",
        "amount": 10.57,
        "price_eur": 1.0,
        "value_eur": 10.57
      },
      {
        "symbol": "LINK",
        "name": "LINK",
        "amount": 0.86982894,
        "price_eur": 7.61,
        "value_eur": 6.62
      }
    ]
  }
}