{
  "updated": "2026-06-24T19:24:35Z",
  "portfolio": {
    "total_invested_eur": 1896.06,
    "total_value_eur": 2601.51,
    "cash_eur": 95.61,
    "total_with_cash": 2697.12,
    "pnl_eur": 705.45,
    "pnl_pct": 37.21,
    "fx_eurusd": 1.1357,
    "positions": [
      {
        "symbol": "NVDA",
        "name": "Nvidia",
        "shares": 4,
        "entry_usd": 191.12,
        "entry_eur": 162.01,
        "current_usd": 197.25,
        "current_eur": 173.68,
        "invested_eur": 648.04,
        "value_eur": 694.71,
        "pnl_eur": 46.67,
        "pnl_pct": 7.2,
        "change_today_pct": -1.39
      },
      {
        "symbol": "GOOGL",
        "name": "Alphabet",
        "shares": 1,
        "entry_usd": 314.19,
        "entry_eur": 266.33,
        "current_usd": 344.91,
        "current_eur": 303.69,
        "invested_eur": 266.33,
        "value_eur": 303.69,
        "pnl_eur": 37.36,
        "pnl_pct": 14.03,
        "change_today_pct": -0.35
      },
      {
        "symbol": "TSM",
        "name": "TSMC",
        "shares": 1,
        "entry_usd": 368.62,
        "entry_eur": 312.47,
        "current_usd": 436.1,
        "current_eur": 383.99,
        "invested_eur": 312.47,
        "value_eur": 383.99,
        "pnl_eur": 71.52,
        "pnl_pct": 22.89,
        "change_today_pct": -0.07
      },
      {
        "symbol": "AMD",
        "name": "Advanced Micro Devices",
        "shares": 2,
        "entry_usd": 196.18,
        "entry_eur": 166.25,
        "current_usd": 508.01,
        "current_eur": 447.3,
        "invested_eur": 332.5,
        "value_eur": 894.61,
        "pnl_eur": 562.11,
        "pnl_pct": 169.05,
        "change_today_pct": -2.28
      },
      {
        "symbol": "MSFT",
        "name": "Microsoft",
        "shares": 1,
        "entry_usd": 397.23,
        "entry_eur": 336.72,
        "current_usd": 368.55,
        "current_eur": 324.51,
        "invested_eur": 336.72,
        "value_eur": 324.51,
        "pnl_eur": -12.21,
        "pnl_pct": -3.63,
        "change_today_pct": -1.44
      }
    ]
  },
  "crypto": {
    "available": true,
    "total_eur": 446.4,
    "holdings": [
      {
        "symbol": "TRUMP",
        "name": "TRUMP",
        "amount": 152.13000794,
        "price_eur": 1.46,
        "value_eur": 222.05
      },
      {
        "symbol": "BTC",
        "name": "BTC",
        "amount": 0.00385803,
        "price_eur": 52508.0,
        "value_eur": 202.58
      },
      {
        "symbol": "EUR",
        "name": "Euro",
        "amount": 7.84,
        "price_eur": 1.0,
        "value_eur": 7.84
      },
      {
        "symbol": "LINK",
        "name": "LINK",
        "amount": 1.10855439,
        "price_eur": 6.34,
        "value_eur": 7.03
      },
      {
        "symbol": "SOL",
        "name": "SOL",
        "amount": 0.1192767,
        "price_eur": 57.88,
        "value_eur": 6.9
      }
    ]
  }
}