{
  "updated": "2026-07-04T09:49:39Z",
  "portfolio": {
    "total_invested_eur": 1896.06,
    "total_value_eur": 2621.88,
    "cash_eur": 95.61,
    "total_with_cash": 2717.49,
    "pnl_eur": 725.82,
    "pnl_pct": 38.28,
    "fx_eurusd": 1.144,
    "positions": [
      {
        "symbol": "NVDA",
        "name": "Nvidia",
        "shares": 4,
        "entry_usd": 191.12,
        "entry_eur": 162.01,
        "current_usd": 194.83,
        "current_eur": 170.3,
        "invested_eur": 648.04,
        "value_eur": 681.2,
        "pnl_eur": 33.16,
        "pnl_pct": 5.12,
        "change_today_pct": -1.39
      },
      {
        "symbol": "GOOGL",
        "name": "Alphabet",
        "shares": 1,
        "entry_usd": 314.19,
        "entry_eur": 266.33,
        "current_usd": 359.91,
        "current_eur": 314.6,
        "invested_eur": 266.33,
        "value_eur": 314.6,
        "pnl_eur": 48.27,
        "pnl_pct": 18.12,
        "change_today_pct": -0.36
      },
      {
        "symbol": "TSM",
        "name": "TSMC",
        "shares": 1,
        "entry_usd": 368.62,
        "entry_eur": 312.47,
        "current_usd": 434.16,
        "current_eur": 379.5,
        "invested_eur": 312.47,
        "value_eur": 379.5,
        "pnl_eur": 67.03,
        "pnl_pct": 21.45,
        "change_today_pct": -2.27
      },
      {
        "symbol": "AMD",
        "name": "Advanced Micro Devices",
        "shares": 2,
        "entry_usd": 196.18,
        "entry_eur": 166.25,
        "current_usd": 517.82,
        "current_eur": 452.63,
        "invested_eur": 332.5,
        "value_eur": 905.25,
        "pnl_eur": 572.75,
        "pnl_pct": 172.26,
        "change_today_pct": -4.26
      },
      {
        "symbol": "MSFT",
        "name": "Microsoft",
        "shares": 1,
        "entry_usd": 397.23,
        "entry_eur": 336.72,
        "current_usd": 390.49,
        "current_eur": 341.33,
        "invested_eur": 336.72,
        "value_eur": 341.33,
        "pnl_eur": 4.61,
        "pnl_pct": 1.37,
        "change_today_pct": 1.62
      }
    ]
  },
  "crypto": {
    "available": true,
    "total_eur": 469.78,
    "holdings": [
      {
        "symbol": "TRUMP",
        "name": "TRUMP",
        "amount": 152.13117473,
        "price_eur": 1.55,
        "value_eur": 235.09
      },
      {
        "symbol": "BTC",
        "name": "BTC",
        "amount": 0.00385803,
        "price_eur": 54607.0,
        "value_eur": 210.68
      },
      {
        "symbol": "SOL",
        "name": "SOL",
        "amount": 0.11930398,
        "price_eur": 71.48,
        "value_eur": 8.53
      },
      {
        "symbol": "EUR",
        "name": "Euro",
        "amount": 7.84,
        "price_eur": 1.0,
        "value_eur": 7.84
      },
      {
        "symbol": "LINK",
        "name": "LINK",
        "amount": 1.10855651,
        "price_eur": 6.9,
        "value_eur": 7.64
      }
    ]
  }
}